{
    "http://publicdomainmovies.info/20000-leagues-sea-1916-film/": {
        "freenessurl": "http://publicdomainmovies.info/20000-leagues-sea-1916-film/",
        "status": "free",
        "title": "20,000 Leagues Under the Sea (1916 film)"
    },
    "http://publicdomainmovies.info/abbott-costellos-africa-screams/": {
        "freenessurl": "http://publicdomainmovies.info/abbott-costellos-africa-screams/",
        "status": "free",
        "title": "Abbott and Costello\u2019s Africa Screams"
    },
    "http://publicdomainmovies.info/abraham-lincoln-1930-film/": {
        "freenessurl": "http://publicdomainmovies.info/abraham-lincoln-1930-film/",
        "status": "free",
        "title": "Abraham Lincoln (1930 film)"
    },
    "http://publicdomainmovies.info/adventures-captain-marvel-1941-serial-chapter-1-curse-scorpion/": {
        "freenessurl": "http://publicdomainmovies.info/adventures-captain-marvel-1941-serial-chapter-1-curse-scorpion/",
        "status": "free",
        "title": "Adventures of Captain Marvel, 1941 (serial) Chapter 1: Curse of the Scorpion"
    },
    "http://publicdomainmovies.info/algiers-1938-charles-boyer/": {
        "freenessurl": "http://publicdomainmovies.info/algiers-1938-charles-boyer/",
        "status": "free",
        "title": "Algiers (1938), with Charles Boyer"
    },
    "http://publicdomainmovies.info/alice-wonderland-1915-film/": {
        "freenessurl": "http://publicdomainmovies.info/alice-wonderland-1915-film/",
        "status": "free",
        "title": "Alice in Wonderland (1915 film)"
    },
    "http://publicdomainmovies.info/amazing-mr-x-full-movie/": {
        "freenessurl": "http://publicdomainmovies.info/amazing-mr-x-full-movie/",
        "status": "free",
        "title": "The Amazing Mr. X [Full Movie]"
    },
    "http://publicdomainmovies.info/angel-badman-1947-starring-john-wayne/": {
        "freenessurl": "http://publicdomainmovies.info/angel-badman-1947-starring-john-wayne/",
        "status": "free",
        "title": "Angel and the Badman (1947), starring John Wayne"
    },
    "http://publicdomainmovies.info/attack-battle-new-britain/": {
        "freenessurl": "http://publicdomainmovies.info/attack-battle-new-britain/",
        "status": "free",
        "title": "Attack! The Battle of New Britain"
    },
    "http://publicdomainmovies.info/attack-giant-leeches-full-movie-public-domain/": {
        "freenessurl": "http://publicdomainmovies.info/attack-giant-leeches-full-movie-public-domain/",
        "status": "free",
        "title": "The Attack of the Giant Leeches \u2013 Full Movie in the Public Domain"
    },
    "http://publicdomainmovies.info/bat-1926-film/": {
        "freenessurl": "http://publicdomainmovies.info/bat-1926-film/",
        "status": "free",
        "title": "The Bat (1926 film)"
    },
    "http://publicdomainmovies.info/beau-brummel-1924/": {
        "freenessurl": "http://publicdomainmovies.info/beau-brummel-1924/",
        "status": "free",
        "title": "Beau Brummel (1924)"
    },
    "http://publicdomainmovies.info/beau-ideal-1931-full-adventure-movie/": {
        "freenessurl": "http://publicdomainmovies.info/beau-ideal-1931-full-adventure-movie/",
        "status": "free",
        "title": "Beau Ideal (1931) \u2013 full adventure movie"
    },
    "http://publicdomainmovies.info/behind-office-doors/": {
        "freenessurl": "http://publicdomainmovies.info/behind-office-doors/",
        "status": "free",
        "title": "Behind Office Doors"
    },
    "http://publicdomainmovies.info/big-cat-1949-film/": {
        "freenessurl": "http://publicdomainmovies.info/big-cat-1949-film/",
        "status": "free",
        "title": "The Big Cat (1949 film)"
    },
    "http://publicdomainmovies.info/big-trees-1952-western-film-starring-kirk-douglas/": {
        "freenessurl": "http://publicdomainmovies.info/big-trees-1952-western-film-starring-kirk-douglas/",
        "status": "free",
        "title": "The Big Trees, 1952 Western film starring Kirk Douglas"
    },
    "http://publicdomainmovies.info/big-wheel-film-starring-mickey-rooney/": {
        "freenessurl": "http://publicdomainmovies.info/big-wheel-film-starring-mickey-rooney/",
        "status": "free",
        "title": "The Big Wheel (film), starring Mickey Rooney"
    },
    "http://publicdomainmovies.info/bird-paradise-1932/": {
        "freenessurl": "http://publicdomainmovies.info/bird-paradise-1932/",
        "status": "free",
        "title": "Bird of Paradise (1932)"
    },
    "http://publicdomainmovies.info/black-pirate-starring-douglas-fairbanks/": {
        "freenessurl": "http://publicdomainmovies.info/black-pirate-starring-douglas-fairbanks/",
        "status": "free",
        "title": "The Black Pirate, starring Douglas Fairbanks"
    },
    "http://publicdomainmovies.info/blood-sand-1922-film-starring-rudolph-valentino/": {
        "freenessurl": "http://publicdomainmovies.info/blood-sand-1922-film-starring-rudolph-valentino/",
        "status": "free",
        "title": "Blood and Sand (1922 film), starring Rudolph Valentino"
    },
    "http://publicdomainmovies.info/blood-sun-starring-james-cagney/": {
        "freenessurl": "http://publicdomainmovies.info/blood-sun-starring-james-cagney/",
        "status": "free",
        "title": "Blood on the Sun, starring James Cagney"
    },
    "http://publicdomainmovies.info/blue-steel-1934-film-john-wayne-u-s-marshal/": {
        "freenessurl": "http://publicdomainmovies.info/blue-steel-1934-film-john-wayne-u-s-marshal/",
        "status": "free",
        "title": "Blue Steel (1934), film with John Wayne as U.S. Marshal"
    },
    "http://publicdomainmovies.info/borrowed-wives-1930/": {
        "freenessurl": "http://publicdomainmovies.info/borrowed-wives-1930/",
        "status": "free",
        "title": "Borrowed Wives, 1930"
    },
    "http://publicdomainmovies.info/bowery-midnight-1942-movie-bela-lugosi/": {
        "freenessurl": "http://publicdomainmovies.info/bowery-midnight-1942-movie-bela-lugosi/",
        "status": "free",
        "title": "Bowery at Midnight, 1942 movie with Bela Lugosi"
    },
    "http://publicdomainmovies.info/brain-wouldnt-die-full-movie/": {
        "freenessurl": "http://publicdomainmovies.info/brain-wouldnt-die-full-movie/",
        "status": "free",
        "title": "The Brain That Wouldn\u2019t Die \u2013 Full Movie"
    },
    "http://publicdomainmovies.info/captain-america-1944-serial-chapter-1-purple-death/": {
        "freenessurl": "http://publicdomainmovies.info/captain-america-1944-serial-chapter-1-purple-death/",
        "status": "free",
        "title": "Captain America, 1944 (serial) chapter 1: The Purple Death"
    },
    "http://publicdomainmovies.info/captain-january-1936-starring-shirley-temple/": {
        "freenessurl": "http://publicdomainmovies.info/captain-january-1936-starring-shirley-temple/",
        "status": "free",
        "title": "Captain January (1936), starring Shirley Temple"
    },
    "http://publicdomainmovies.info/carmen-1915-directed-cecil-b-demille/": {
        "freenessurl": "http://publicdomainmovies.info/carmen-1915-directed-cecil-b-demille/",
        "status": "free",
        "title": "Carmen, 1915 directed by Cecil B. DeMille"
    },
    "http://publicdomainmovies.info/carnival-souls-1962/": {
        "freenessurl": "http://publicdomainmovies.info/carnival-souls-1962/",
        "status": "free",
        "title": "Carnival of Souls (1962)"
    },
    "http://publicdomainmovies.info/charade-1963-cary-grant-audrey-hepburn-best-hitchcock-movie-hitchcock-never-made/": {
        "freenessurl": "http://publicdomainmovies.info/charade-1963-cary-grant-audrey-hepburn-best-hitchcock-movie-hitchcock-never-made/",
        "status": "free",
        "title": "Charade (1963), Cary Grant and Audrey Hepburn in the \u201cthe best Hitchcock movie that Hitchcock never made\u201d"
    },
    "http://publicdomainmovies.info/charlie-chaplin-kid-auto-race-venice/": {
        "freenessurl": "http://publicdomainmovies.info/charlie-chaplin-kid-auto-race-venice/",
        "status": "free",
        "title": "Charlie Chaplin: The Kid Auto Race in Venice"
    },
    "http://publicdomainmovies.info/charlie-chaplin-making-living/": {
        "freenessurl": "http://publicdomainmovies.info/charlie-chaplin-making-living/",
        "status": "free",
        "title": "Charlie Chaplin: Making a Living"
    },
    "http://publicdomainmovies.info/charlie-chaplins-kid-1921-film-one-greatest-films-silent-era/": {
        "freenessurl": "http://publicdomainmovies.info/charlie-chaplins-kid-1921-film-one-greatest-films-silent-era/",
        "status": "free",
        "title": "Charlie Chaplin\u2019s The Kid (1921 film), one of the greatest films of the silent era"
    },
    "http://publicdomainmovies.info/cheat-1915-directed-cecil-b-demille/": {
        "freenessurl": "http://publicdomainmovies.info/cheat-1915-directed-cecil-b-demille/",
        "status": "free",
        "title": "The Cheat, 1915 directed by Cecil B. DeMille"
    },
    "http://publicdomainmovies.info/check-double-check/": {
        "freenessurl": "http://publicdomainmovies.info/check-double-check/",
        "status": "free",
        "title": "Check and Double Check"
    },
    "http://publicdomainmovies.info/cinderella-1914-film-starring-mary-pickford/": {
        "freenessurl": "http://publicdomainmovies.info/cinderella-1914-film-starring-mary-pickford/",
        "status": "free",
        "title": "Cinderella 1914 film starring Mary Pickford"
    },
    "http://publicdomainmovies.info/colonel-effinghams-raid-charles-coburn-joan-bennett-william-eythe/": {
        "freenessurl": "http://publicdomainmovies.info/colonel-effinghams-raid-charles-coburn-joan-bennett-william-eythe/",
        "status": "free",
        "title": "Colonel Effingham\u2019s Raid, with Charles Coburn, Joan Bennett and William Eythe"
    },
    "http://publicdomainmovies.info/combat-america-clark-gable/": {
        "freenessurl": "http://publicdomainmovies.info/combat-america-clark-gable/",
        "status": "free",
        "title": "Combat America with Clark Gable"
    },
    "http://publicdomainmovies.info/conspiracy-1930-film/": {
        "freenessurl": "http://publicdomainmovies.info/conspiracy-1930-film/",
        "status": "free",
        "title": "Conspiracy (1930 film)"
    },
    "http://publicdomainmovies.info/cyrano-de-bergerac-1950/": {
        "freenessurl": "http://publicdomainmovies.info/cyrano-de-bergerac-1950/",
        "status": "free",
        "title": "Cyrano de Bergerac (1950)"
    },
    "http://publicdomainmovies.info/d-o-a-1949/": {
        "freenessurl": "http://publicdomainmovies.info/d-o-a-1949/",
        "status": "free",
        "title": "D.O.A. (1949)"
    },
    "http://publicdomainmovies.info/daddy-long-legs-1919-film/": {
        "freenessurl": "http://publicdomainmovies.info/daddy-long-legs-1919-film/",
        "status": "free",
        "title": "Daddy-Long-Legs (1919 film)"
    },
    "http://publicdomainmovies.info/dance-life-1929-full-movie/": {
        "freenessurl": "http://publicdomainmovies.info/dance-life-1929-full-movie/",
        "status": "free",
        "title": "The Dance of Life (1929) \u2013 Full Movie"
    },
    "http://publicdomainmovies.info/danger-lights/": {
        "freenessurl": "http://publicdomainmovies.info/danger-lights/",
        "status": "free",
        "title": "Danger Lights"
    },
    "http://publicdomainmovies.info/dangerous-game-big-game-hunter-hunts-humans-sport/": {
        "freenessurl": "http://publicdomainmovies.info/dangerous-game-big-game-hunter-hunts-humans-sport/",
        "status": "free",
        "title": "The Most Dangerous Game, a big game hunter who hunts humans for sport"
    },
    "http://publicdomainmovies.info/deadly-companions-starring-maureen-ohara-directed-sam-peckinpah/": {
        "freenessurl": "http://publicdomainmovies.info/deadly-companions-starring-maureen-ohara-directed-sam-peckinpah/",
        "status": "free",
        "title": "The Deadly Companions, starring Maureen O\u2019Hara and directed by Sam Peckinpah"
    },
    "http://publicdomainmovies.info/delightfully-dangerous-1945/": {
        "freenessurl": "http://publicdomainmovies.info/delightfully-dangerous-1945/",
        "status": "free",
        "title": "Delightfully Dangerous, 1945"
    },
    "http://publicdomainmovies.info/detour-1945-film-movie/": {
        "freenessurl": "http://publicdomainmovies.info/detour-1945-film-movie/",
        "status": "free",
        "title": "Detour (1945 film) [Full Movie]"
    },
    "http://publicdomainmovies.info/devil-bat-starring-bela-lugosi-pre-vampire-movie/": {
        "freenessurl": "http://publicdomainmovies.info/devil-bat-starring-bela-lugosi-pre-vampire-movie/",
        "status": "free",
        "title": "The Devil Bat, starring Bela Lugosi in a pre-vampire movie!"
    },
    "http://publicdomainmovies.info/dick-tracy-1937-serial-chapter-1-spider-strikes/": {
        "freenessurl": "http://publicdomainmovies.info/dick-tracy-1937-serial-chapter-1-spider-strikes/",
        "status": "free",
        "title": "Dick Tracy, 1937 (serial) chapter 1: The Spider Strikes"
    },
    "http://publicdomainmovies.info/dixiana-film/": {
        "freenessurl": "http://publicdomainmovies.info/dixiana-film/",
        "status": "free",
        "title": "Dixiana (film)"
    },
    "http://publicdomainmovies.info/dr-jekyll-mr-hyde-1920-film/": {
        "freenessurl": "http://publicdomainmovies.info/dr-jekyll-mr-hyde-1920-film/",
        "status": "free",
        "title": "Dr. Jekyll and Mr. Hyde (1920 film)"
    },
    "http://publicdomainmovies.info/dream-street-1921-directed-d-w-griffith/": {
        "freenessurl": "http://publicdomainmovies.info/dream-street-1921-directed-d-w-griffith/",
        "status": "free",
        "title": "Dream Street, 1921 directed by D. W. Griffith"
    },
    "http://publicdomainmovies.info/ed-woods-bride-monster-1955-starring-bela-lugosi/": {
        "freenessurl": "http://publicdomainmovies.info/ed-woods-bride-monster-1955-starring-bela-lugosi/",
        "status": "free",
        "title": "Ed Wood\u2019s Bride of the Monster, 1955 starring Bela Lugosi"
    },
    "http://publicdomainmovies.info/fast-furious-1955-film-john-ireland-dorothy-malone/": {
        "freenessurl": "http://publicdomainmovies.info/fast-furious-1955-film-john-ireland-dorothy-malone/",
        "status": "free",
        "title": "The Fast and the Furious, 1955 film with John Ireland and Dorothy Malone"
    },
    "http://publicdomainmovies.info/fathers-little-dividend-1951-starring-spencer-tracy-joan-bennett-elizabeth-taylor/": {
        "freenessurl": "http://publicdomainmovies.info/fathers-little-dividend-1951-starring-spencer-tracy-joan-bennett-elizabeth-taylor/",
        "status": "free",
        "title": "Father\u2019s Little Dividend, 1951 \u2013 starring Spencer Tracy, Joan Bennett and Elizabeth Taylor"
    },
    "http://publicdomainmovies.info/fight-sky-narrated-ronald-reagan/": {
        "freenessurl": "http://publicdomainmovies.info/fight-sky-narrated-ronald-reagan/",
        "status": "free",
        "title": "The Fight for the Sky, narrated by Ronald Reagan"
    },
    "http://publicdomainmovies.info/five-minutes-live-1961-johnny-cash/": {
        "freenessurl": "http://publicdomainmovies.info/five-minutes-live-1961-johnny-cash/",
        "status": "free",
        "title": "Five Minutes to Live, 1961 with Johnny Cash"
    },
    "http://publicdomainmovies.info/flash-gordon-conquers-universe-tv-serial-chapter-1-purple-death/": {
        "freenessurl": "http://publicdomainmovies.info/flash-gordon-conquers-universe-tv-serial-chapter-1-purple-death/",
        "status": "free",
        "title": "Flash Gordon Conquers the Universe (serial), chapter 1: The Purple Death"
    },
    "http://publicdomainmovies.info/foolish-wives-1922/": {
        "freenessurl": "http://publicdomainmovies.info/foolish-wives-1922/",
        "status": "free",
        "title": "Foolish Wives, 1922"
    },
    "http://publicdomainmovies.info/for-you-i-die-1947/": {
        "freenessurl": "http://publicdomainmovies.info/for-you-i-die-1947/",
        "status": "free",
        "title": "For You I Die, 1947"
    },
    "http://publicdomainmovies.info/francis-ford-coppolas-dementia-13/": {
        "freenessurl": "http://publicdomainmovies.info/francis-ford-coppolas-dementia-13/",
        "status": "free",
        "title": "Francis Ford Coppola\u2019s Dementia 13"
    },
    "http://publicdomainmovies.info/frank-capras-meet-john-doe/": {
        "freenessurl": "http://publicdomainmovies.info/frank-capras-meet-john-doe/",
        "status": "free",
        "title": "Frank Capra\u2019s Meet John Doe"
    },
    "http://publicdomainmovies.info/frankenstein-1910-film/": {
        "freenessurl": "http://publicdomainmovies.info/frankenstein-1910-film/",
        "status": "free",
        "title": "Frankenstein (1910 film)"
    },
    "http://publicdomainmovies.info/general-buster-keaton-1926-film/": {
        "freenessurl": "http://publicdomainmovies.info/general-buster-keaton-1926-film/",
        "status": "free",
        "title": "The General \u2013 Buster Keaton (1926 film)"
    },
    "http://publicdomainmovies.info/girl-friday-1940-directed-howard-hawks-starring-cary-grant-rosalind-russell/": {
        "freenessurl": "http://publicdomainmovies.info/girl-friday-1940-directed-howard-hawks-starring-cary-grant-rosalind-russell/",
        "status": "free",
        "title": "His Girl Friday, 1940 directed by Howard Hawks and starring Cary Grant and Rosalind Russell"
    },
    "http://publicdomainmovies.info/glen-glenda-1953-ed-wood/": {
        "freenessurl": "http://publicdomainmovies.info/glen-glenda-1953-ed-wood/",
        "status": "free",
        "title": "Glen or Glenda \u2013 1953 \u2013 Ed Wood"
    },
    "http://publicdomainmovies.info/go-broke-1951-film-starring-van-johnson/": {
        "freenessurl": "http://publicdomainmovies.info/go-broke-1951-film-starring-van-johnson/",
        "status": "free",
        "title": "Go for Broke! (1951 film), starring Van Johnson"
    },
    "http://publicdomainmovies.info/gods-little-acre-film/": {
        "freenessurl": "http://publicdomainmovies.info/gods-little-acre-film/",
        "status": "free",
        "title": "God\u2019s Little Acre (film)"
    },
    "http://publicdomainmovies.info/gold-rush-1925-charlie-chaplin/": {
        "freenessurl": "http://publicdomainmovies.info/gold-rush-1925-charlie-chaplin/",
        "status": "free",
        "title": "The Gold Rush, 1925 by Charlie Chaplin"
    },
    "http://publicdomainmovies.info/gorilla-1939-film/": {
        "freenessurl": "http://publicdomainmovies.info/gorilla-1939-film/",
        "status": "free",
        "title": "The Gorilla (1939 film)"
    },
    "http://publicdomainmovies.info/great-guy-1936-movie-starring-james-cagney-mae-clarke/": {
        "freenessurl": "http://publicdomainmovies.info/great-guy-1936-movie-starring-james-cagney-mae-clarke/",
        "status": "free",
        "title": "Great Guy, 1936 movie starring James Cagney and Mae Clarke"
    },
    "http://publicdomainmovies.info/greeks-word-full-movie/": {
        "freenessurl": "http://publicdomainmovies.info/greeks-word-full-movie/",
        "status": "free",
        "title": "The Greeks Had a Word for Them, full movie"
    },
    "http://publicdomainmovies.info/gullivers-travels-1939/": {
        "freenessurl": "http://publicdomainmovies.info/gullivers-travels-1939/",
        "status": "free",
        "title": "Gullivers Travels (1939)"
    },
    "http://publicdomainmovies.info/half-shot-sunrise-american-comedy-film-starring-comedy-duo-wheeler-woolsey/": {
        "freenessurl": "http://publicdomainmovies.info/half-shot-sunrise-american-comedy-film-starring-comedy-duo-wheeler-woolsey/",
        "status": "free",
        "title": "Half Shot at Sunrise, American comedy film starring the comedy duo Wheeler & Woolsey"
    },
    "http://publicdomainmovies.info/hells-hinges-1916/": {
        "freenessurl": "http://publicdomainmovies.info/hells-hinges-1916/",
        "status": "free",
        "title": "Hell\u2019s Hinges, 1916"
    },
    "http://publicdomainmovies.info/hi-de-ho-1947-musical/": {
        "freenessurl": "http://publicdomainmovies.info/hi-de-ho-1947-musical/",
        "status": "free",
        "title": "Hi-De-Ho (1947 musical)"
    },
    "http://publicdomainmovies.info/high-voltage-1929-film-starring-carole-lombard/": {
        "freenessurl": "http://publicdomainmovies.info/high-voltage-1929-film-starring-carole-lombard/",
        "status": "free",
        "title": "High Voltage, 1929 film starring Carole Lombard"
    },
    "http://publicdomainmovies.info/hook-line-sinker-1930-film/": {
        "freenessurl": "http://publicdomainmovies.info/hook-line-sinker-1930-film/",
        "status": "free",
        "title": "Hook, Line and Sinker (1930 film)"
    },
    "http://publicdomainmovies.info/house-haunted-hill-vincent-price-carol-ohmart/": {
        "freenessurl": "http://publicdomainmovies.info/house-haunted-hill-vincent-price-carol-ohmart/",
        "status": "free",
        "title": "House on Haunted Hill, with Vincent Price and Carol Ohmart"
    },
    "http://publicdomainmovies.info/human-bondage-1934-bette-davis/": {
        "freenessurl": "http://publicdomainmovies.info/human-bondage-1934-bette-davis/",
        "status": "free",
        "title": "Of Human Bondage (1934), with Bette Davis"
    },
    "http://publicdomainmovies.info/hunchback-notre-dame-1923/": {
        "freenessurl": "http://publicdomainmovies.info/hunchback-notre-dame-1923/",
        "status": "free",
        "title": "The Hunchback of Notre Dame (1923)"
    },
    "http://publicdomainmovies.info/indestructible-man/": {
        "freenessurl": "http://publicdomainmovies.info/indestructible-man/",
        "status": "free",
        "title": "Indestructible Man, 1956"
    },
    "http://publicdomainmovies.info/inside-lines-1930/": {
        "freenessurl": "http://publicdomainmovies.info/inside-lines-1930/",
        "status": "free",
        "title": "Inside the Lines, 1930"
    },
    "http://publicdomainmovies.info/italian-1915-film/": {
        "freenessurl": "http://publicdomainmovies.info/italian-1915-film/",
        "status": "free",
        "title": "The Italian (1915 film)"
    },
    "http://publicdomainmovies.info/japan-1945-propaganda-film/": {
        "freenessurl": "http://publicdomainmovies.info/japan-1945-propaganda-film/",
        "status": "free",
        "title": "My Japan, 1945 propaganda film"
    },
    "http://publicdomainmovies.info/joan-woman-1916-directed-cecil-b-demille/": {
        "freenessurl": "http://publicdomainmovies.info/joan-woman-1916-directed-cecil-b-demille/",
        "status": "free",
        "title": "Joan the Woman, 1916 directed by Cecil B. DeMille"
    },
    "http://publicdomainmovies.info/jungle-book1942-film/": {
        "freenessurl": "http://publicdomainmovies.info/jungle-book1942-film/",
        "status": "free",
        "title": "Jungle Book,1942 film"
    },
    "http://publicdomainmovies.info/kept-husbands-1931/": {
        "freenessurl": "http://publicdomainmovies.info/kept-husbands-1931/",
        "status": "free",
        "title": "Kept Husbands, 1931"
    },
    "http://publicdomainmovies.info/land-head-hunters-1914/": {
        "freenessurl": "http://publicdomainmovies.info/land-head-hunters-1914/",
        "status": "free",
        "title": "In the Land of the Head Hunters, 1914"
    },
    "http://publicdomainmovies.info/last-clear-chance-1959/": {
        "freenessurl": "http://publicdomainmovies.info/last-clear-chance-1959/",
        "status": "free",
        "title": "Last Clear Chance (1959)"
    },
    "http://publicdomainmovies.info/last-man-earth-vincent-price-1964-hd/": {
        "freenessurl": "http://publicdomainmovies.info/last-man-earth-vincent-price-1964-hd/",
        "status": "free",
        "title": "LAST MAN ON EARTH with Vincent Price 1964 HD"
    },
    "http://publicdomainmovies.info/last-mohicans-1920-american-film/": {
        "freenessurl": "http://publicdomainmovies.info/last-mohicans-1920-american-film/",
        "status": "free",
        "title": "The Last of the Mohicans (1920 American film)"
    },
    "http://publicdomainmovies.info/last-time-saw-paris-1954-starring-elizabeth-taylor-van-johnson/": {
        "freenessurl": "http://publicdomainmovies.info/last-time-saw-paris-1954-starring-elizabeth-taylor-van-johnson/",
        "status": "free",
        "title": "The Last Time I Saw Paris (1954), starring Elizabeth Taylor and Van Johnson"
    },
    "http://publicdomainmovies.info/leopard-woman-1920/": {
        "freenessurl": "http://publicdomainmovies.info/leopard-woman-1920/",
        "status": "free",
        "title": "The Leopard Woman, 1920"
    },
    "http://publicdomainmovies.info/little-princess-1939-film-starring-shirley-temple/": {
        "freenessurl": "http://publicdomainmovies.info/little-princess-1939-film-starring-shirley-temple/",
        "status": "free",
        "title": "The Little Princess (1939 film), starring Shirley Temple"
    },
    "http://publicdomainmovies.info/little-shop-horrors/": {
        "freenessurl": "http://publicdomainmovies.info/little-shop-horrors/",
        "status": "free",
        "title": "The Little Shop Of Horrors"
    },
    "http://publicdomainmovies.info/lone-ranger-tv-serial-chapter-1-hi-yo-silver/": {
        "freenessurl": "http://publicdomainmovies.info/lone-ranger-tv-serial-chapter-1-hi-yo-silver/",
        "status": "free",
        "title": "The Lone Ranger (serial), chapter 1: Hi-Yo Silver"
    },
    "http://publicdomainmovies.info/lonely-wives-full-movie/": {
        "freenessurl": "http://publicdomainmovies.info/lonely-wives-full-movie/",
        "status": "free",
        "title": "Lonely Wives \u2013 full movie"
    },
    "http://publicdomainmovies.info/lost-world-1925-film/": {
        "freenessurl": "http://publicdomainmovies.info/lost-world-1925-film/",
        "status": "free",
        "title": "The Lost World (1925 film)"
    },
    "http://publicdomainmovies.info/love-affair-1939-film/": {
        "freenessurl": "http://publicdomainmovies.info/love-affair-1939-film/",
        "status": "free",
        "title": "Love Affair (1939 film)"
    },
    "http://publicdomainmovies.info/lucky-texan-1934-john-wayne/": {
        "freenessurl": "http://publicdomainmovies.info/lucky-texan-1934-john-wayne/",
        "status": "free",
        "title": "The Lucky Texan (1934), with John Wayne"
    },
    "http://publicdomainmovies.info/majesty-scarecrow-oz-1914/": {
        "freenessurl": "http://publicdomainmovies.info/majesty-scarecrow-oz-1914/",
        "status": "free",
        "title": "His Majesty, the Scarecrow of Oz, 1914"
    },
    "http://publicdomainmovies.info/man-without-country-1917-film/": {
        "freenessurl": "http://publicdomainmovies.info/man-without-country-1917-film/",
        "status": "free",
        "title": "The Man Without a Country, 1917 film"
    },
    "http://publicdomainmovies.info/manos-hands-fate-1966/": {
        "freenessurl": "http://publicdomainmovies.info/manos-hands-fate-1966/",
        "status": "free",
        "title": "Manos: The Hands of Fate, 1966"
    },
    "http://publicdomainmovies.info/mark-zorro-1920-film-starring-douglas-fairbanks-noah-beery/": {
        "freenessurl": "http://publicdomainmovies.info/mark-zorro-1920-film-starring-douglas-fairbanks-noah-beery/",
        "status": "free",
        "title": "The Mark of Zorro (1920 film), starring Douglas Fairbanks and Noah Beery"
    },
    "http://publicdomainmovies.info/mormon-maid-1917/": {
        "freenessurl": "http://publicdomainmovies.info/mormon-maid-1917/",
        "status": "free",
        "title": "A Mormon Maid, 1917"
    },
    "http://publicdomainmovies.info/mystery-liner-1934/": {
        "freenessurl": "http://publicdomainmovies.info/mystery-liner-1934/",
        "status": "free",
        "title": "Mystery Liner, 1934"
    },
    "http://publicdomainmovies.info/night-ghouls-1958-movie-directed-ed-wood/": {
        "freenessurl": "http://publicdomainmovies.info/night-ghouls-1958-movie-directed-ed-wood/",
        "status": "free",
        "title": "Night of the Ghouls, 1958 movie directed by Ed Wood"
    },
    "http://publicdomainmovies.info/night-of-the-living-dead-1968/": {
        "freenessurl": "http://publicdomainmovies.info/night-of-the-living-dead-1968/",
        "status": "free",
        "title": "Night of the Living Dead (1968)"
    },
    "http://publicdomainmovies.info/oliver-twist-1922-film-featuring-lon-chaney/": {
        "freenessurl": "http://publicdomainmovies.info/oliver-twist-1922-film-featuring-lon-chaney/",
        "status": "free",
        "title": "Oliver Twist (1922 film), featuring Lon Chaney"
    },
    "http://publicdomainmovies.info/outlaw-1943-directed-howard-hughes-starring-jane-russell/": {
        "freenessurl": "http://publicdomainmovies.info/outlaw-1943-directed-howard-hughes-starring-jane-russell/",
        "status": "free",
        "title": "The Outlaw (1943), directed by Howard Hughes and starring Jane Russell"
    },
    "http://publicdomainmovies.info/penalty-1920-film/": {
        "freenessurl": "http://publicdomainmovies.info/penalty-1920-film/",
        "status": "free",
        "title": "The Penalty (1920 film)"
    },
    "http://publicdomainmovies.info/phantom-empire-70-mins-feature-film/": {
        "freenessurl": "http://publicdomainmovies.info/phantom-empire-70-mins-feature-film/",
        "status": "free",
        "title": "The Phantom Empire, 70 mins feature film"
    },
    "http://publicdomainmovies.info/phantom-opera-1925-film/": {
        "freenessurl": "http://publicdomainmovies.info/phantom-opera-1925-film/",
        "status": "free",
        "title": "The Phantom of the Opera (1925 film)"
    },
    "http://publicdomainmovies.info/plan-9-outer-space-1959-worst-movie-ever-made-starring-bela-lugosi/": {
        "freenessurl": "http://publicdomainmovies.info/plan-9-outer-space-1959-worst-movie-ever-made-starring-bela-lugosi/",
        "status": "free",
        "title": "Plan 9 from Outer Space (1959) \u2013 \u201cworst movie ever made\u201d, starring Bela Lugosi"
    },
    "http://publicdomainmovies.info/pride-clan-1917-starring-mary-pickford/": {
        "freenessurl": "http://publicdomainmovies.info/pride-clan-1917-starring-mary-pickford/",
        "status": "free",
        "title": "The Pride of the Clan, 1917 starring Mary Pickford"
    },
    "http://publicdomainmovies.info/radar-men-moon-1952-serial-chapter-1-moon-rocket/": {
        "freenessurl": "http://publicdomainmovies.info/radar-men-moon-1952-serial-chapter-1-moon-rocket/",
        "status": "free",
        "title": "Radar Men from the Moon, 1952 (serial) chapter 1: Moon Rocket"
    },
    "http://publicdomainmovies.info/rain-1932-film-starring-joan-crawford-prostitute/": {
        "freenessurl": "http://publicdomainmovies.info/rain-1932-film-starring-joan-crawford-prostitute/",
        "status": "free",
        "title": "Rain (1932 film), starring Joan Crawford as a prostitute"
    },
    "http://publicdomainmovies.info/reefer-madness-one-worst-films-ever-made/": {
        "freenessurl": "http://publicdomainmovies.info/reefer-madness-one-worst-films-ever-made/",
        "status": "free",
        "title": "Reefer Madness, \u201cone of the worst films ever made\u201d"
    },
    "http://publicdomainmovies.info/regeneration-1915-film/": {
        "freenessurl": "http://publicdomainmovies.info/regeneration-1915-film/",
        "status": "free",
        "title": "Regeneration, 1915 film"
    },
    "http://publicdomainmovies.info/resisting-enemy-interrogation-1944/": {
        "freenessurl": "http://publicdomainmovies.info/resisting-enemy-interrogation-1944/",
        "status": "free",
        "title": "Resisting Enemy Interrogation, 1944"
    },
    "http://publicdomainmovies.info/riders-destiny-1933-john-wayne-singing-cowboy/": {
        "freenessurl": "http://publicdomainmovies.info/riders-destiny-1933-john-wayne-singing-cowboy/",
        "status": "free",
        "title": "Riders of Destiny (1933), with John Wayne as a singing cowboy"
    },
    "http://publicdomainmovies.info/road-bali-1952-starring-bing-crosby-bob-hope-dorothy-lamour/": {
        "freenessurl": "http://publicdomainmovies.info/road-bali-1952-starring-bing-crosby-bob-hope-dorothy-lamour/",
        "status": "free",
        "title": "Road To Bali (1952), starring Bing Crosby, Bob Hope, Dorothy Lamour"
    },
    "http://publicdomainmovies.info/robin-hood-1922-film-starring-douglas-fairbanks/": {
        "freenessurl": "http://publicdomainmovies.info/robin-hood-1922-film-starring-douglas-fairbanks/",
        "status": "free",
        "title": "Robin Hood (1922 film), starring Douglas Fairbanks"
    },
    "http://publicdomainmovies.info/rock-rock-rock-film-chuck-berry-flamingos-teenagers-frankie-lymon/": {
        "freenessurl": "http://publicdomainmovies.info/rock-rock-rock-film-chuck-berry-flamingos-teenagers-frankie-lymon/",
        "status": "free",
        "title": "Rock, Rock, Rock (film), with Chuck Berry, the Flamingos, and the Teenagers with Frankie Lymon"
    },
    "http://publicdomainmovies.info/romance-redwoods-1917-directed-cecil-b-demille/": {
        "freenessurl": "http://publicdomainmovies.info/romance-redwoods-1917-directed-cecil-b-demille/",
        "status": "free",
        "title": "A Romance of the Redwoods, 1917 directed by Cecil B. DeMille"
    },
    "http://publicdomainmovies.info/santa-claus-conquers-martians/": {
        "freenessurl": "http://publicdomainmovies.info/santa-claus-conquers-martians/",
        "status": "free",
        "title": "Santa Claus Conquers the Martians"
    },
    "http://publicdomainmovies.info/santa-fe-trail-1940-ronald-reagan-errol-flynn-olivia-de-havilland/": {
        "freenessurl": "http://publicdomainmovies.info/santa-fe-trail-1940-ronald-reagan-errol-flynn-olivia-de-havilland/",
        "status": "free",
        "title": "Santa Fe Trail (1940) \u2013 Ronald Reagan, Errol Flynn and Olivia de Havilland"
    },
    "http://publicdomainmovies.info/seven-years-bad-luck-1921/": {
        "freenessurl": "http://publicdomainmovies.info/seven-years-bad-luck-1921/",
        "status": "free",
        "title": "Seven Years Bad Luck, 1921"
    },
    "http://publicdomainmovies.info/shadows-1922-film-starring-lon-chaney/": {
        "freenessurl": "http://publicdomainmovies.info/shadows-1922-film-starring-lon-chaney/",
        "status": "free",
        "title": "Shadows (1922 film), starring Lon Chaney"
    },
    "http://publicdomainmovies.info/sherlock-holmes-1922-film/": {
        "freenessurl": "http://publicdomainmovies.info/sherlock-holmes-1922-film/",
        "status": "free",
        "title": "Sherlock Holmes (1922 film)"
    },
    "http://publicdomainmovies.info/sherlock-holmes-secret-weapon-1942-basil-rathbone-nigel-bruce/": {
        "freenessurl": "http://publicdomainmovies.info/sherlock-holmes-secret-weapon-1942-basil-rathbone-nigel-bruce/",
        "status": "free",
        "title": "Sherlock Holmes and the Secret Weapon (1942) with Basil Rathbone & Nigel Bruce"
    },
    "http://publicdomainmovies.info/shoulda-said-no-1949-exploitation-film/": {
        "freenessurl": "http://publicdomainmovies.info/shoulda-said-no-1949-exploitation-film/",
        "status": "free",
        "title": "She Shoulda Said No!, 1949 exploitation film"
    },
    "http://publicdomainmovies.info/sky-high-1922-film/": {
        "freenessurl": "http://publicdomainmovies.info/sky-high-1922-film/",
        "status": "free",
        "title": "Sky High (1922 film)"
    },
    "http://publicdomainmovies.info/smouldering-fires-film/": {
        "freenessurl": "http://publicdomainmovies.info/smouldering-fires-film/",
        "status": "free",
        "title": "Smouldering Fires (film)"
    },
    "http://publicdomainmovies.info/snow-white-1916-film/": {
        "freenessurl": "http://publicdomainmovies.info/snow-white-1916-film/",
        "status": "free",
        "title": "Snow White, 1916 film"
    },
    "http://publicdomainmovies.info/snows-kilimanjaro-1952-starring-gregory-peck-susan-hayward-ava-gardner/": {
        "freenessurl": "http://publicdomainmovies.info/snows-kilimanjaro-1952-starring-gregory-peck-susan-hayward-ava-gardner/",
        "status": "free",
        "title": "The Snows of Kilimanjaro (1952), starring Gregory Peck, Susan Hayward and Ava Gardner"
    },
    "http://publicdomainmovies.info/star-born-1937-full-movie/": {
        "freenessurl": "http://publicdomainmovies.info/star-born-1937-full-movie/",
        "status": "free",
        "title": "A Star Is Born (1937 full movie)"
    },
    "http://publicdomainmovies.info/steamboat-bill-jr-1928-buster-keaton/": {
        "freenessurl": "http://publicdomainmovies.info/steamboat-bill-jr-1928-buster-keaton/",
        "status": "free",
        "title": "Steamboat Bill, Jr., 1928 with Buster Keaton"
    },
    "http://publicdomainmovies.info/stranger-1946-orson-wells-directs-edward-g-robinson/": {
        "freenessurl": "http://publicdomainmovies.info/stranger-1946-orson-wells-directs-edward-g-robinson/",
        "status": "free",
        "title": "The Stranger (1946), Orson Wells directs Edward G. Robinson"
    },
    "http://publicdomainmovies.info/tangled-trails-1921/": {
        "freenessurl": "http://publicdomainmovies.info/tangled-trails-1921/",
        "status": "free",
        "title": "Tangled Trails, 1921"
    },
    "http://publicdomainmovies.info/tango-tangles-1914-charles-chaplin-roscoe-arbuckle/": {
        "freenessurl": "http://publicdomainmovies.info/tango-tangles-1914-charles-chaplin-roscoe-arbuckle/",
        "status": "free",
        "title": "Tango Tangles (1914) \u2013 Charles Chaplin and Roscoe Arbuckle"
    },
    "http://publicdomainmovies.info/tarzan-apes-1918-film/": {
        "freenessurl": "http://publicdomainmovies.info/tarzan-apes-1918-film/",
        "status": "free",
        "title": "Tarzan of the Apes (1918 film)"
    },
    "http://publicdomainmovies.info/teenagers-outer-space/": {
        "freenessurl": "http://publicdomainmovies.info/teenagers-outer-space/",
        "status": "free",
        "title": "Teenagers From Outer Space"
    },
    "http://publicdomainmovies.info/terror-1963-film-boris-karloff-jack-nicholson/": {
        "freenessurl": "http://publicdomainmovies.info/terror-1963-film-boris-karloff-jack-nicholson/",
        "status": "free",
        "title": "The Terror (1963 film), with Boris Karloff and Jack Nicholson"
    },
    "http://publicdomainmovies.info/the-animal-kingdom/": {
        "freenessurl": "http://publicdomainmovies.info/the-animal-kingdom/",
        "status": "free",
        "title": "The Animal Kingdom"
    },
    "http://publicdomainmovies.info/the-flapper-1920/": {
        "freenessurl": "http://publicdomainmovies.info/the-flapper-1920/",
        "status": "free",
        "title": "The Flapper, 1920"
    },
    "http://publicdomainmovies.info/three-musketeers-1921-film/": {
        "freenessurl": "http://publicdomainmovies.info/three-musketeers-1921-film/",
        "status": "free",
        "title": "The Three Musketeers (1921 film)"
    },
    "http://publicdomainmovies.info/three-stooges-brideless-groom/": {
        "freenessurl": "http://publicdomainmovies.info/three-stooges-brideless-groom/",
        "status": "free",
        "title": "The Three Stooges: Brideless Groom"
    },
    "http://publicdomainmovies.info/three-stooges-disorder-court/": {
        "freenessurl": "http://publicdomainmovies.info/three-stooges-disorder-court/",
        "status": "free",
        "title": "Three Stooges: Disorder In The Court"
    },
    "http://publicdomainmovies.info/three-stooges-malice-palace/": {
        "freenessurl": "http://publicdomainmovies.info/three-stooges-malice-palace/",
        "status": "free",
        "title": "Three Stooges: Malice In The Palace"
    },
    "http://publicdomainmovies.info/through-the-back-door/": {
        "freenessurl": "http://publicdomainmovies.info/through-the-back-door/",
        "status": "free",
        "title": "Through the Back Door"
    },
    "http://publicdomainmovies.info/till-clouds-roll-1946-judy-garland-frank-sinatra/": {
        "freenessurl": "http://publicdomainmovies.info/till-clouds-roll-1946-judy-garland-frank-sinatra/",
        "status": "free",
        "title": "Till The Clouds Roll by (1946), with Judy Garland and Frank Sinatra"
    },
    "http://publicdomainmovies.info/tom-sawyer-1917-film-starring-jack-pickford/": {
        "freenessurl": "http://publicdomainmovies.info/tom-sawyer-1917-film-starring-jack-pickford/",
        "status": "free",
        "title": "Tom Sawyer, 1917 film starring Jack Pickford"
    },
    "http://publicdomainmovies.info/trip-moon-georges-melies-1902/": {
        "freenessurl": "http://publicdomainmovies.info/trip-moon-georges-melies-1902/",
        "status": "free",
        "title": "A Trip to the Moon (Georges M\u00e9li\u00e8s, 1902)"
    },
    "http://publicdomainmovies.info/violent-years-1956/": {
        "freenessurl": "http://publicdomainmovies.info/violent-years-1956/",
        "status": "free",
        "title": "The Violent Years, 1956"
    },
    "http://publicdomainmovies.info/virginian-1914-film-directed-cecil-b-demille/": {
        "freenessurl": "http://publicdomainmovies.info/virginian-1914-film-directed-cecil-b-demille/",
        "status": "free",
        "title": "The Virginian (1914 film), directed by Cecil B. DeMille"
    },
    "http://publicdomainmovies.info/west-hot-dog-starring-stan-laurel/": {
        "freenessurl": "http://publicdomainmovies.info/west-hot-dog-starring-stan-laurel/",
        "status": "free",
        "title": "West of Hot Dog, starring Stan Laurel"
    },
    "http://publicdomainmovies.info/white-zombie-full-movie-1932-bela-lugosi/": {
        "freenessurl": "http://publicdomainmovies.info/white-zombie-full-movie-1932-bela-lugosi/",
        "status": "free",
        "title": "White Zombie (full movie, 1932), with Bela Lugosi"
    },
    "http://publicdomainmovies.info/woman-green-basil-rathbone-sherlock-holmes-nigel-bruce-dr-watson/": {
        "freenessurl": "http://publicdomainmovies.info/woman-green-basil-rathbone-sherlock-holmes-nigel-bruce-dr-watson/",
        "status": "free",
        "title": "The Woman in Green, with Basil Rathbone as Sherlock Holmes and Nigel Bruce as Dr. Watson"
    },
    "http://publicdomainmovies.info/wonderful-wizard-oz-1910-film/": {
        "freenessurl": "http://publicdomainmovies.info/wonderful-wizard-oz-1910-film/",
        "status": "free",
        "title": "The Wonderful Wizard of Oz (1910 film)"
    },
    "http://publicdomainmovies.info/worldly-madonna-1922/": {
        "freenessurl": "http://publicdomainmovies.info/worldly-madonna-1922/",
        "status": "free",
        "title": "The Worldly Madonna, 1922"
    },
    "http://publicdomainmovies.info/zorro-rides-again1937-serial-chapter-1-death-sky/": {
        "freenessurl": "http://publicdomainmovies.info/zorro-rides-again1937-serial-chapter-1-death-sky/",
        "status": "free",
        "title": "Zorro Rides Again, 1937 (serial) Chapter 1: Death from the Sky"
    },
    "http://publicdomainmovies.info/zorros-black-whip-1944-tv-serial-chapter-1-masked-avenger/": {
        "freenessurl": "http://publicdomainmovies.info/zorros-black-whip-1944-tv-serial-chapter-1-masked-avenger/",
        "status": "free",
        "title": "Zorro\u2019s Black Whip, 1944 (serial), chapter 1: The Masked Avenger"
    },
    "http://publicdomainmovies.info/zorros-fighting-legion-1939-serial-chapter-1-golden-god/": {
        "freenessurl": "http://publicdomainmovies.info/zorros-fighting-legion-1939-serial-chapter-1-golden-god/",
        "status": "free",
        "title": "Zorro\u2019s Fighting Legion, 1939 (serial) Chapter 1: Golden God"
    }
}